dousatsu/__init__.py
dousatsu/feature_analysis.py
dousatsu/feature_preprocessing.py
dousatsu/feature_selection.py
dousatsu/feature_visualization.py
dousatsu-0.1.3.dist-info/licenses/LICENSE
dousatsu-0.1.3.dist-info/METADATA
dousatsu-0.1.3.dist-info/WHEEL
dousatsu-0.1.3.dist-info/top_level.txt
dousatsu-0.1.3.dist-info/RECORD
