Metadata-Version: 2.4
Name: dousatsu
Version: 0.1.3
Summary: Utility functions for proteomics data analysis
Author-email: Pedrioli Patrick <pedrioli@gmail.com>
License: LICENSE
License-File: LICENSE
Requires-Dist: numpy
Requires-Dist: pandas
Requires-Dist: scikit-learn
Requires-Dist: seaborn
Requires-Dist: pyteomics
Requires-Dist: statsmodels
Requires-Dist: plotly
Requires-Dist: networkx
Requires-Dist: scipy
Requires-Dist: matplotlib
Provides-Extra: dev
Requires-Dist: pre-commit; extra == "dev"
Requires-Dist: build; extra == "dev"
Requires-Dist: twine; extra == "dev"
Requires-Dist: deptry; extra == "dev"
Requires-Dist: tox; extra == "dev"
Dynamic: license-file
